rosbag_util/__init__.py
rosbag_util/_version.py
rosbag_util/cli.py
rosbag_util/extract.py
rosbag_util/merge_multi_pcd.py
rosbag_util/undistort_images.py
rosbag_util/__pycache__/__init__.cpython-38.pyc
rosbag_util/__pycache__/cli.cpython-38.pyc
rosbag_util/__pycache__/extract.cpython-38.pyc
rosbag_util-1.0.6.dist-info/METADATA
rosbag_util-1.0.6.dist-info/WHEEL
rosbag_util-1.0.6.dist-info/entry_points.txt
rosbag_util-1.0.6.dist-info/top_level.txt
rosbag_util-1.0.6.dist-info/RECORD
