Metadata-Version: 2.4
Name: rosbag-util
Version: 1.0.6
Summary: Utilities for extracting synchronized frames from ROS bag files.
Author: keiyo
License: MIT
Requires-Python: >=3.8
Requires-Dist: numpy
Requires-Dist: open3d
Requires-Dist: Pillow
Requires-Dist: tomli; python_version < "3.11"
Requires-Dist: opencv-python
